django_pipeline_storage-0.0.1.dist-info/DESCRIPTION.rst
django_pipeline_storage-0.0.1.dist-info/METADATA
django_pipeline_storage-0.0.1.dist-info/RECORD
django_pipeline_storage-0.0.1.dist-info/WHEEL
django_pipeline_storage-0.0.1.dist-info/metadata.json
django_pipeline_storage-0.0.1.dist-info/top_level.txt
pipeline_storage/__init__.py
pipeline_storage/storage.py
