Metadata-Version: 2.0
Name: django-pipeline-storage
Version: 0.0.1
Summary: A simple Storage finder for files when django-pipeline is develop mode.
Home-page: https://github.com/leonardoo/pipeline-storage
Author: Leonardo orozco
Author-email: leonardoorozcop@gmail.com
License: MIT
Platform: UNKNOWN
Classifier: Development Status :: 3 - Alpha
Classifier: Topic :: Software Development :: Build Tools
Classifier: Environment :: Web Environment
Classifier: Framework :: Django
Classifier: Intended Audience :: Developers
Classifier: License :: OSI Approved :: MIT License
Classifier: Operating System :: OS Independent
Classifier: Programming Language :: Python
Classifier: Programming Language :: Python :: 2
Classifier: Programming Language :: Python :: 3
